gitlab2mr/__init__.py
gitlab2mr/__main__.py
gitlab2mr/cli.py
gitlab2mr-0.2.4.dist-info/LICENSE
gitlab2mr-0.2.4.dist-info/METADATA
gitlab2mr-0.2.4.dist-info/WHEEL
gitlab2mr-0.2.4.dist-info/entry_points.txt
gitlab2mr-0.2.4.dist-info/top_level.txt
gitlab2mr-0.2.4.dist-info/RECORD
