Metadata-Version: 2.1
Name: gitlab2mr
Version: 0.2.4
Summary: A gitlab-to-myrepo config helper
Home-page: https://github.com/pyscaffold/pyscaffold/
Author: Jonas Schlagenhauf
Author-email: schlagenhauf_github@mailbox.org
License: MIT
Project-URL: Source, https://github.com/schlagenhauf/gitlab2mr
Platform: any
Classifier: Development Status :: 4 - Beta
Classifier: Programming Language :: Python
Classifier: License :: OSI Approved :: GNU General Public License (GPL)
License-File: LICENSE
Requires-Dist: python-gitlab
Requires-Dist: click
Requires-Dist: importlib-metadata ; python_version < "3.8"
Provides-Extra: testing
Requires-Dist: setuptools ; extra == 'testing'
